textlong/__PROMPTS__/chat/RAG/main.mu
textlong/__PROMPTS__/writing/FROM_OUTLINE/example.mu
textlong/__PROMPTS__/writing/FROM_OUTLINE/instruction.mu
textlong/__PROMPTS__/writing/FROM_OUTLINE/task_todo.mu
textlong/__PROMPTS__/writing/MORE_OUTLINE/example.mu
textlong/__PROMPTS__/writing/MORE_OUTLINE/instruction.mu
textlong/__PROMPTS__/writing/MORE_OUTLINE/task_todo.mu
textlong/__PROMPTS__/writing/OUTLINE/example.mu
textlong/__PROMPTS__/writing/OUTLINE/instruction.mu
textlong/__PROMPTS__/writing/SUMMARISE/task_todo.mu
textlong/__PROMPTS__/writing/history.mu
textlong/__PROMPTS__/writing/knowledge.mu
textlong/__PROMPTS__/writing/main.mu
textlong/__PROMPTS__/writing/task_desc.mu
textlong/__PROMPTS__/writing/task_todo.mu
textlong/__init__.py
textlong/__version__.py
textlong/agents/__init__.py
textlong/agents/base.py
textlong/agents/prompt.py
textlong/agents/tools_calling.py
textlong/chain/__init__.py
textlong/chain/qa.py
textlong/chain/write.py
textlong/config/__init__.py
textlong/config/base.py
textlong/exporter/__init__.py
textlong/exporter/docx.py
textlong/exporter/html.py
textlong/exporter/jupyter.py
textlong/exporter/pptx.py
textlong/fastapi/__init__.py
textlong/fastapi/auth.py
textlong/fastapi/project.py
textlong/fastapi/whitelist.py
textlong/hub/__init__.py
textlong/hub/resource.py
textlong/importer/__init__.py
textlong/importer/md.py
textlong/knowledge/__init__.py
textlong/knowledge/base.py
textlong/knowledge/qa_excel.py
textlong/memory/__init__.py
textlong/memory/base.py
textlong/memory/file_store.py
textlong/memory/memory_manager.py
textlong/parser/__init__.py
textlong/parser/docx.py
textlong/parser/markdown.py
textlong/project/__init__.py
textlong/project/base.py
textlong/project/projects.py
textlong/utils.py
textlong/writing/__init__.py
textlong/writing/base.py
textlong/writing/command.py
textlong/writing/markdown.py
textlong/writing/message.py
textlong-0.4.15.dist-info/LICENSE
textlong-0.4.15.dist-info/METADATA
textlong-0.4.15.dist-info/WHEEL
textlong-0.4.15.dist-info/RECORD
