Metadata-Version: 2.1
Name: textlong
Version: 0.4.15
Summary: A framework designed to produce long-texts with GPT or other large language models.
Home-page: https://github.com/arcstep/textlong
License: MIT
Author: arcstep
Author-email: 43801@qq.com
Requires-Python: >=3.10,<4
Classifier: License :: OSI Approved :: MIT License
Classifier: Programming Language :: Python :: 3
Classifier: Programming Language :: Python :: 3.10
Classifier: Programming Language :: Python :: 3.11
Classifier: Programming Language :: Python :: 3.12
Requires-Dist: fastapi (>=0.111.0,<0.112.0)
Requires-Dist: langchain (>=0.1.0,<0.3.0)
Requires-Dist: langchain-community (>=0.0.38,<0.3.0)
Requires-Dist: langchain-zhipu (>=4.1.6,<5.0.0)
Requires-Dist: mistune (>=3.0.2,<4.0.0)
Requires-Dist: openpyxl (>=3.1.4,<4.0.0)
Requires-Dist: pandas (>=2.2.2,<3.0.0)
Requires-Dist: pydantic (>=1,<3)
Requires-Dist: python-jose (>=3.3.0,<4.0.0)
Project-URL: Repository, https://github.com/arcstep/textlong.git
